datelibrary/__init__.py
datelibrary/dates.py
datelibrary_javis-0.1.0.dist-info/LICENSE
datelibrary_javis-0.1.0.dist-info/METADATA
datelibrary_javis-0.1.0.dist-info/WHEEL
datelibrary_javis-0.1.0.dist-info/top_level.txt
datelibrary_javis-0.1.0.dist-info/RECORD
