Metadata-Version: 2.1
Name: datelibrary-javis
Version: 0.1.0
Summary: date package for parsing dates
Home-page: https://github.com/pypa/sampleproject
Author: javis
Author-email: admin@javis.in
License: UNKNOWN
Platform: UNKNOWN
Classifier: Programming Language :: Python :: 3
Classifier: License :: OSI Approved :: MIT License
Classifier: Operating System :: OS Independent
Requires-Python: >=3.6
